{
  "project_info": {
    "project_number": "643881133335",
    "project_id": "fc-ch02-realtime-quiz",
    "storage_bucket": "fc-ch02-realtime-quiz.firebasestorage.app"
  },
  "client": [
    {
      "client_info": {
        "mobilesdk_app_id": "1:643881133335:android:8130850bf97ed1cb1e0352",
        "android_client_info": {
          "package_name": "com.example.ch02_realtime_quiz"
        }
      },
      "oauth_client": [],
      "api_key": [
        {
          "current_key": "AIzaSyBF4-ka4JMPCjrCs75kFAmWFVKgAEg-oUM"
        }
      ],
      "services": {
        "appinvite_service": {
          "other_platform_oauth_client": []
        }
      }
    }
  ],
  "configuration_version": "1"
}